torchloader/__init__.py
torchloader/dataloader.py
torchloader/dataset.py
torchloader/sampler.py
torchloader-0.2.1.dist-info/DESCRIPTION.rst
torchloader-0.2.1.dist-info/METADATA
torchloader-0.2.1.dist-info/RECORD
torchloader-0.2.1.dist-info/WHEEL
torchloader-0.2.1.dist-info/metadata.json
torchloader-0.2.1.dist-info/top_level.txt
