Metadata-Version: 2.0
Name: torchloader
Version: 0.2.1
Summary: A PyTorch style dataloader that can be used anywhere
Home-page: https://github.com/lematt1991/DataLoader
Author: Matt Le
Author-email: lematt1991@gmail.com
License: UNKNOWN
Download-URL: https://github.com/lematt1991/DataLoader/archive/master.zip
Keywords: dataloader,pytorch,torch,multiprocess
Platform: UNKNOWN
